prettytree/PrettyTree.py
prettytree/__init__.py
prettytree-0.1.3.dist-info/LICENSE
prettytree-0.1.3.dist-info/METADATA
prettytree-0.1.3.dist-info/WHEEL
prettytree-0.1.3.dist-info/top_level.txt
prettytree-0.1.3.dist-info/RECORD
