Metadata-Version: 2.1
Name: prettytree
Version: 0.1.3
Summary: Simple generator of tree data structure for your dirs
Home-page: https://github.com/Fadix47/prettytree
Author: Fadix Meier
Author-email: fadix18123@gmail.com
Project-URL: Bug Tracker, https://github.com/Fadix47/prettytree/issues
Classifier: Programming Language :: Python :: 3
Classifier: License :: OSI Approved :: MIT License
Classifier: Operating System :: OS Independent
Requires-Python: >=3.7
License-File: LICENSE
